tests/__init__.py
tests/test_traductor_cron.py
traductor_cron/__init__.py
traductor_cron/traductor_cron.py
traductor_cron-0.1.1.dist-info/LICENSE
traductor_cron-0.1.1.dist-info/METADATA
traductor_cron-0.1.1.dist-info/WHEEL
traductor_cron-0.1.1.dist-info/top_level.txt
traductor_cron-0.1.1.dist-info/RECORD
