Metadata-Version: 2.1
Name: traductor_cron
Version: 0.1.1
Summary: Una librería para traducir expresiones cron al español y calcular próximas ejecuciones.
Home-page: https://github.com/ClauMS/traductor_cron
Author: Claudiano Maniega
Author-email: cmaniega@ovosoftware.cl
Classifier: Programming Language :: Python :: 3
Classifier: License :: OSI Approved :: MIT License
Classifier: Operating System :: OS Independent
Requires-Python: >=3.7
License-File: LICENSE
Requires-Dist: croniter
